semaflow/__init__.py
semaflow/api.py
semaflow/core.py
semaflow/handle.py
semaflow/semaflow.cpython-312-darwin.so
semaflow/semaflow.pyi
semaflow-0.1.2.dist-info/METADATA
semaflow-0.1.2.dist-info/WHEEL
semaflow-0.1.2.dist-info/licenses/LICENSE
semaflow-0.1.2.dist-info/RECORD
