Metadata-Version: 2.4
Name: semaflow
Version: 0.1.2
Classifier: Development Status :: 4 - Beta
Classifier: Intended Audience :: Developers
Classifier: Topic :: Database
Classifier: Programming Language :: Python :: 3.12
Classifier: Programming Language :: Rust
Requires-Dist: pyyaml>=6.0
Requires-Dist: semaflow[arrow,api,dev] ; extra == 'all'
Requires-Dist: fastapi[standard]>=0.122.0 ; extra == 'api'
Requires-Dist: uvicorn[standard]>=0.23.0 ; extra == 'api'
Requires-Dist: orjson>=3.9.0 ; extra == 'api'
Requires-Dist: pyarrow>=14.0.0 ; extra == 'arrow'
Requires-Dist: pyarrow>=14.0.0 ; extra == 'dev'
Requires-Dist: pandas>=2.0.0 ; extra == 'dev'
Requires-Dist: maturin>=1.10.2 ; extra == 'dev'
Requires-Dist: pytest>=8.0 ; extra == 'dev'
Requires-Dist: pytest-asyncio>=0.24 ; extra == 'dev'
Requires-Dist: httpx>=0.27 ; extra == 'dev'
Provides-Extra: all
Provides-Extra: api
Provides-Extra: arrow
Provides-Extra: dev
License-File: LICENSE
Summary: Semantic layer for analytical databases
Keywords: semantic-layer,analytics,sql,duckdb,bigquery,postgres
Home-Page: https://github.com/SemaFlow-labs/SemaFlow
Author: JCart97
Requires-Python: >=3.12
Project-URL: Homepage, https://github.com/SemaFlow-labs/SemaFlow
Project-URL: Repository, https://github.com/SemaFlow-labs/SemaFlow
